<?xml version="1.0" encoding="UTF-8"?>

<!DOCTYPE tiles-definitions PUBLIC "-//Apache Software Foundation//DTD Tiles Configuration 3.0//EN"
"http://tiles.apache.org/dtds/tiles-config_3_0.dtd">

<tiles-definitions>
    <definition name="basePage" template="/WEB-INF/layout/base.jsp">
        <put-attribute name="title" value="" />
        <put-attribute name="header" value="/WEB-INF/layout/header.jsp" />
        <put-attribute name="content" value="" />
        <put-attribute name="footer" value="/WEB-INF/layout/footer.jsp" />
    </definition>
    <definition name="homeAdmin" extends="basePage">
        <put-attribute name="title" value="Admin" />
        <put-attribute name="content" value="/WEB-INF/pages/index.jsp" />
    </definition>

    <definition name="notification" extends="basePage">
        <put-attribute name="title" value="Notification" />
        <put-attribute name="content" value="/WEB-INF/pages/notification.jsp" />
    </definition>
    <definition name="statsUser" extends="basePage">
        <put-attribute name="title" value="Stats" />
        <put-attribute name="content" value="/WEB-INF/pages/stats.jsp" />
    </definition>
    <definition name="users" extends="basePage">
        <put-attribute name="title" value="Users" />
        <put-attribute name="content" value="/WEB-INF/pages/user.jsp" />
    </definition>
    <definition name="statsPost" extends="basePage">
        <put-attribute name="title" value="StatsPost" />
        <put-attribute name="content" value="/WEB-INF/pages/statsPost.jsp" />
    </definition>
    <definition name="statsYear" extends="basePage">
        <put-attribute name="title" value="StatsYear" />
        <put-attribute name="content" value="/WEB-INF/pages/statsYear.jsp" />
    </definition>
    <definition name="post" extends="basePage">
        <put-attribute name="title" value="Post" />
        <put-attribute name="content" value="/WEB-INF/pages/post.jsp" />
    </definition>
    <definition name="login" extends="basePage">
        <put-attribute name="title" value="Login" />
        <put-attribute name="content" value="/WEB-INF/pages/login.jsp" />
    </definition>
    <definition name="post" extends="baseLayout">
        <put-attribute name="title" value="Thêm bài dang" />
        <put-attribute name="content" value="/WEB-INF/pages/post.jsp" />
    </definition>
    
</tiles-definitions>